croniters-0.2.1.dist-info/METADATA
croniters-0.2.1.dist-info/WHEEL
croniters-0.2.1.dist-info/licenses/LICENSE
croniters/__init__.py
croniters/_croniters.pyi
croniters/_croniters.cpython-313t-aarch64-linux-gnu.so
croniters-0.2.1.dist-info/RECORD
