Metadata-Version: 2.4
Name: croniters
Version: 0.2.1
Classifier: Programming Language :: Rust
Classifier: Programming Language :: Python :: Implementation :: CPython
Classifier: Programming Language :: Python :: Implementation :: PyPy
Requires-Dist: python-dateutil
Requires-Dist: pytz>2021.1
License-File: LICENSE
Summary: A port of python's `croniter` package in Rust and exposed on PyPI via `pyo3` as `croniters`.
Requires-Python: >=3.8
